{"completed_in":0.124,"max_id":115518060542181376,"max_id_str":"115518060542181376","next_page":"?page=6&max_id=115518060542181376&q=cuteoverload.com&lang=en&rpp=100","previous_page":"?page=4&max_id=115518060542181376&q=cuteoverload.com&lang=en&rpp=100","page":5,"query":"cuteoverload.com","refresh_url":"?since_id=115518060542181376&q=cuteoverload.com&lang=en","results":[{"created_at":"Sun, 18 Sep 2011 20:10:26 +0000","from_user":"HomeStudioArts","from_user_id":5393077,"from_user_id_str":"5393077","geo":null,"id":115518060542181376,"id_str":"115518060542181376","iso_language_code":"en","metadata":{"result_type":"recent"},"profile_image_url":"http://a1.twimg.com/profile_images/1288707532/il_fullxfull_normal.jpg","source":"&lt;a href=&quot;http://twitterfeed.com&quot; rel=&quot;nofollow&quot;&gt;twitterfeed&lt;/a&gt;","text":"OK\u2014who abandon this seal pup!?: Alert Cuteporters Jennifer C. and Phil P. is reporting that a rare albino seal p... http://t.co/klKLs5nq","to_user_id":null,"to_user_id_str":null},{"created_at":"Sun, 18 Sep 2011 20:10:26 +0000","from_user":"eweirdworld","from_user_id":66199583,"from_user_id_str":"66199583","geo":null,"id":115518060319866880,"id_str":"115518060319866880","iso_language_code":"en","metadata":{"result_type":"recent"},"profile_image_url":"http://a3.twimg.com/profile_images/1302439371/gravatar_normal.jpg","source":"&lt;a href=&quot;http://twitterfeed.com&quot; rel=&quot;nofollow&quot;&gt;twitterfeed&lt;/a&gt;","text":"OK\u2014who abandon this seal pup!?: Alert Cuteporters Jennifer C. and Phil P. is reporting that a rare a... http://t.co/qy95HHa5 #cute #pets","to_user_id":null,"to_user_id_str":null},{"created_at":"Sun, 18 Sep 2011 20:10:26 +0000","from_user":"KawaiiFriends","from_user_id":82117293,"from_user_id_str":"82117293","geo":null,"id":115518059384545280,"id_str":"115518059384545280","iso_language_code":"en","metadata":{"result_type":"recent"},"profile_image_url":"http://a1.twimg.com/profile_images/557255464/tco-avatar_normal.jpg","source":"&lt;a href=&quot;http://twitterfeed.com&quot; rel=&quot;nofollow&quot;&gt;twitterfeed&lt;/a&gt;","text":"Cute Overload Post! OK\u2014who abandon this seal pup!?: Alert Cuteporters Jennifer C. and Phil P... http://t.co/w5i6WTio #cuteoverload #cute","to_user_id":null,"to_user_id_str":null},{"created_at":"Sun, 18 Sep 2011 20:10:26 +0000","from_user":"lolcute","from_user_id":6554815,"from_user_id_str":"6554815","geo":null,"id":115518059296473089,"id_str":"115518059296473089","iso_language_code":"en","metadata":{"result_type":"recent"},"profile_image_url":"http://a1.twimg.com/profile_images/91106120/sleep-in-bowl_normal.png","source":"&lt;a href=&quot;http://twitterfeed.com&quot; rel=&quot;nofollow&quot;&gt;twitterfeed&lt;/a&gt;","text":"OK\u2014who abandon this seal pup!? http://t.co/QWQmUIHK","to_user_id":null,"to_user_id_str":null},{"created_at":"Sun, 18 Sep 2011 20:09:40 +0000","from_user":"CuteOverload","from_user_id":692409,"from_user_id_str":"692409","geo":null,"id":115517868220743680,"id_str":"115517868220743680","iso_language_code":"en","metadata":{"result_type":"recent"},"profile_image_url":"http://a1.twimg.com/profile_images/97078327/co_normal.png","source":"&lt;a href=&quot;http://publicize.wp.com/&quot; rel=&quot;nofollow&quot;&gt;WordPress.com&lt;/a&gt;","text":"OK\u2014who abandon this seal pup!? http://t.co/3hshpU1s","to_user_id":null,"to_user_id_str":null},{"created_at":"Sun, 18 Sep 2011 19:31:37 +0000","from_user":"GeekyChris","from_user_id":401860856,"from_user_id_str":"401860856","geo":null,"id":115508293513916416,"id_str":"115508293513916416","iso_language_code":"en","metadata":{"result_type":"recent"},"profile_image_url":"http://a3.twimg.com/profile_images/1528938148/Photo_on_2011-09-01_at_19.44_normal.jpg","source":"&lt;a href=&quot;http://twitter.com/&quot;&gt;web&lt;/a&gt;","text":"@cfheaney http://t.co/rAHrrQrF /via @wordpressdotcom","to_user":"cfheaney","to_user_id":228328,"to_user_id_str":"228328"},{"created_at":"Sun, 18 Sep 2011 19:24:07 +0000","from_user":"Marybethsueann","from_user_id":9105141,"from_user_id_str":"9105141","geo":null,"id":115506405104029696,"id_str":"115506405104029696","iso_language_code":"en","metadata":{"result_type":"recent"},"profile_image_url":"http://a3.twimg.com/profile_images/1405848546/avatar_normal.JPEG","source":"&lt;a href=&quot;http://twitter.com/tweetbutton&quot; rel=&quot;nofollow&quot;&gt;Tweet Button&lt;/a&gt;","text":"Enough already George Lucas!  PS...gotta see this one!  You've Gone Too Far, George Lucas http://t.co/aSxKdxi7 /via @wordpressdotcom","to_user_id":null,"to_user_id_str":null},{"created_at":"Sun, 18 Sep 2011 18:47:53 +0000","from_user":"isaiahmathews","from_user_id":361357654,"from_user_id_str":"361357654","geo":null,"id":115497286657785857,"id_str":"115497286657785857","iso_language_code":"en","metadata":{"result_type":"recent"},"profile_image_url":"http://a2.twimg.com/profile_images/1540727391/image_normal.jpg","source":"&lt;a href=&quot;http://www.nibirutech.com/mobilerss-google-reader-iphone.html&quot; rel=&quot;nofollow&quot;&gt;MobileRSS&lt;/a&gt;","text":"Cute Overload - Must be a Jimmy Chew shoe http://t.co/7yoZbbXJ","to_user_id":null,"to_user_id_str":null},{"created_at":"Sun, 18 Sep 2011 18:43:44 +0000","from_user":"marikoth","from_user_id":79417768,"from_user_id_str":"79417768","geo":null,"id":115496241240092673,"id_str":"115496241240092673","iso_language_code":"en","metadata":{"result_type":"recent"},"profile_image_url":"http://a0.twimg.com/profile_images/1458886195/DSC02159__1__normal.jpg","source":"&lt;a href=&quot;http://twitter.com/#!/download/iphone&quot; rel=&quot;nofollow&quot;&gt;Twitter for iPhone&lt;/a&gt;","text":"Incredibly painful result. I couldn't watch any more football after the game today! I had to escape to cuteoverload.com wonderland... #LFC","to_user_id":null,"to_user_id_str":null},{"created_at":"Sun, 18 Sep 2011 18:42:32 +0000","from_user":"jaci_blackee","from_user_id":124121257,"from_user_id_str":"124121257","geo":null,"id":115495940546248706,"id_str":"115495940546248706","iso_language_code":"en","metadata":{"result_type":"recent"},"profile_image_url":"http://a0.twimg.com/profile_images/1523026666/Snapshot_of_me_1_normal.jpg","source":"&lt;a href=&quot;http://twitter.com/download/android&quot; rel=&quot;nofollow&quot;&gt;Twitter for Android&lt;/a&gt;","text":"&quot;@Pais2Blaze: Cutest thing ever. For you @jaci_blackee http://t.co/NKep9PpH&quot; omg, I died ...","to_user_id":null,"to_user_id_str":null},{"created_at":"Sun, 18 Sep 2011 18:38:58 +0000","from_user":"Pais2Blaze","from_user_id":401099750,"from_user_id_str":"401099750","geo":null,"id":115495042046627840,"id_str":"115495042046627840","iso_language_code":"en","metadata":{"result_type":"recent"},"profile_image_url":"http://a1.twimg.com/profile_images/1526943619/yay2_normal","source":"&lt;a href=&quot;http://www.alphonsolabs.com/&quot; rel=&quot;nofollow&quot;&gt;Pulse News&lt;/a&gt;","text":"Cutest thing ever. For you @jaci_blackee http://t.co/k0XNYuyG","to_user_id":null,"to_user_id_str":null},{"created_at":"Sun, 18 Sep 2011 18:29:49 +0000","from_user":"Zoe_Smith","from_user_id":6232419,"from_user_id_str":"6232419","geo":null,"id":115492738845245440,"id_str":"115492738845245440","iso_language_code":"en","metadata":{"result_type":"recent"},"profile_image_url":"http://a2.twimg.com/profile_images/1495111524/76401184-ac66-4dd0-af6d-90621dd886d3_normal.jpg","source":"&lt;a href=&quot;http://www.tweetdeck.com&quot; rel=&quot;nofollow&quot;&gt;TweetDeck&lt;/a&gt;","text":"shall we continue? http://t.co/AiYk2cRB for my 20000th tweet. Have you seen this? http://t.co/9TiXswpd #tortoise","to_user_id":null,"to_user_id_str":null},{"created_at":"Sun, 18 Sep 2011 18:24:40 +0000","from_user":"cutedepot","from_user_id":206698103,"from_user_id_str":"206698103","geo":null,"id":115491444403355648,"id_str":"115491444403355648","iso_language_code":"en","metadata":{"result_type":"recent"},"profile_image_url":"http://a0.twimg.com/profile_images/1345525208/cutedepot_normal.jpg","source":"&lt;a href=&quot;http://dlvr.it&quot; rel=&quot;nofollow&quot;&gt;dlvr.it&lt;/a&gt;","text":"Must be a Jimmy Chew shoe http://t.co/rIRWFnfV","to_user_id":null,"to_user_id_str":null},{"created_at":"Sun, 18 Sep 2011 18:23:33 +0000","from_user":"mrsoblivious","from_user_id":43671106,"from_user_id_str":"43671106","geo":null,"id":115491163384979456,"id_str":"115491163384979456","iso_language_code":"en","metadata":{"result_type":"recent"},"profile_image_url":"http://a3.twimg.com/profile_images/1463721095/DSCF3686_6_normal.jpg","source":"&lt;a href=&quot;http://twitter.com/&quot;&gt;web&lt;/a&gt;","text":"RT @CuteOverload via @LizzieSkys  My cats would love to do THIS  Kitty Jedi  http://t.co/TQ2qNZ29","to_user_id":null,"to_user_id_str":null},{"created_at":"Sun, 18 Sep 2011 17:17:00 +0000","from_user":"carpeamorlklk","from_user_id":35910381,"from_user_id_str":"35910381","geo":null,"id":115474414723801088,"id_str":"115474414723801088","iso_language_code":"en","metadata":{"result_type":"recent"},"profile_image_url":"http://a0.twimg.com/profile_images/1259131504/IMG_0144_normal.jpg","source":"&lt;a href=&quot;http://twitter.com/tweetbutton&quot; rel=&quot;nofollow&quot;&gt;Tweet Button&lt;/a&gt;","text":"Ladies and Gentlemen, The Cutest Kitten in the World http://t.co/ED6EFbi3 /via @wordpressdotcom","to_user_id":null,"to_user_id_str":null},{"created_at":"Sun, 18 Sep 2011 17:12:07 +0000","from_user":"tripleoverload","from_user_id":571463,"from_user_id_str":"571463","geo":null,"id":115473184358281216,"id_str":"115473184358281216","iso_language_code":"en","metadata":{"result_type":"recent"},"profile_image_url":"http://a1.twimg.com/profile_images/28458812/baru_1_normal.jpg","source":"&lt;a href=&quot;http://twitterfeed.com&quot; rel=&quot;nofollow&quot;&gt;twitterfeed&lt;/a&gt;","text":"[cute*] Must be a Jimmy Chew shoe http://t.co/1o6gYJCe","to_user_id":null,"to_user_id_str":null},{"created_at":"Sun, 18 Sep 2011 17:11:51 +0000","from_user":"lindsaygmorriso","from_user_id":398108688,"from_user_id_str":"398108688","geo":null,"id":115473117517852674,"id_str":"115473117517852674","iso_language_code":"en","metadata":{"result_type":"recent"},"profile_image_url":"http://a2.twimg.com/profile_images/1426477112/10953_170661226129_536051129_2919225_4729777_n_normal.jpg","source":"&lt;a href=&quot;http://twitter.com/tweetbutton&quot; rel=&quot;nofollow&quot;&gt;Tweet Button&lt;/a&gt;","text":"@TheMarlaElf    LOLpug = Little Old Lady Pug http://t.co/VpKIywFU /via @wordpressdotcom","to_user":"TheMarlaElf","to_user_id":369196505,"to_user_id_str":"369196505"},{"created_at":"Sun, 18 Sep 2011 17:09:49 +0000","from_user":"chloemcgill","from_user_id":117509280,"from_user_id_str":"117509280","geo":null,"id":115472606588698625,"id_str":"115472606588698625","iso_language_code":"en","metadata":{"result_type":"recent"},"profile_image_url":"http://a1.twimg.com/profile_images/1152153353/frog_normal.jpg","source":"&lt;a href=&quot;http://www.feedblitz.com/f/f.fbz?help/default#twitter&quot; rel=&quot;nofollow&quot;&gt;FeedBlitz&lt;/a&gt;","text":"Must be a Jimmy Chew shoe via Cute Overload - Remember, always thoroughly chew your food. It's better for ... http://t.co/DRipPipe","to_user_id":null,"to_user_id_str":null},{"created_at":"Sun, 18 Sep 2011 17:00:02 +0000","from_user":"LearnSales","from_user_id":262492423,"from_user_id_str":"262492423","geo":null,"id":115470145362722816,"id_str":"115470145362722816","iso_language_code":"en","metadata":{"result_type":"recent"},"profile_image_url":"http://a2.twimg.com/profile_images/1309943199/30154_518077057863_60201317_30666749_8187519_n_normal.jpg","source":"&lt;a href=&quot;http://twitterfeed.com&quot; rel=&quot;nofollow&quot;&gt;twitterfeed&lt;/a&gt;","text":"Must be a Jimmy Chew shoe http://t.co/VvLfCTW4","to_user_id":null,"to_user_id_str":null},{"created_at":"Sun, 18 Sep 2011 16:56:29 +0000","from_user":"TeresaMilligan","from_user_id":7061088,"from_user_id_str":"7061088","geo":null,"id":115469249455206402,"id_str":"115469249455206402","iso_language_code":"en","metadata":{"result_type":"recent"},"profile_image_url":"http://a0.twimg.com/profile_images/1410713328/profile_normal.jpg","source":"&lt;a href=&quot;http://publicize.wp.com/&quot; rel=&quot;nofollow&quot;&gt;WordPress.com&lt;/a&gt;","text":"RT @CuteOverload: It's Caturday Night so I brought the Glow Kitten http://t.co/Surn6uCP","to_user_id":null,"to_user_id_str":null},{"created_at":"Sun, 18 Sep 2011 16:53:50 +0000","from_user":"RakhaSN","from_user_id":395769744,"from_user_id_str":"395769744","geo":null,"id":115468583865294848,"id_str":"115468583865294848","iso_language_code":"en","metadata":{"result_type":"recent"},"profile_image_url":"http://a3.twimg.com/profile_images/1506232602/313165_267454843264797_100000008494660_1153381_7258134_n_normal.jpg","source":"&lt;a href=&quot;http://twitterfeed.com&quot; rel=&quot;nofollow&quot;&gt;twitterfeed&lt;/a&gt;","text":"Must be a Jimmy Chew shoe: Remember, always thoroughly chew your food. It\u2019s better for your digestive system.\n\nC... http://t.co/av7Aznn0","to_user_id":null,"to_user_id_str":null},{"created_at":"Sun, 18 Sep 2011 16:53:50 +0000","from_user":"AmandaBosten","from_user_id":366365277,"from_user_id_str":"366365277","geo":null,"id":115468583814955008,"id_str":"115468583814955008","iso_language_code":"en","metadata":{"result_type":"recent"},"profile_image_url":"http://a0.twimg.com/profile_images/1453901349/p3ihy_normal.jpg","source":"&lt;a href=&quot;http://twitterfeed.com&quot; rel=&quot;nofollow&quot;&gt;twitterfeed&lt;/a&gt;","text":"Must be a Jimmy Chew shoe: Remember, always thoroughly chew your food. It\u2019s better for your digestive system.\n\nC... http://t.co/MBFVVGtw","to_user_id":null,"to_user_id_str":null},{"created_at":"Sun, 18 Sep 2011 16:53:50 +0000","from_user":"eweirdworld","from_user_id":66199583,"from_user_id_str":"66199583","geo":null,"id":115468583454253056,"id_str":"115468583454253056","iso_language_code":"en","metadata":{"result_type":"recent"},"profile_image_url":"http://a3.twimg.com/profile_images/1302439371/gravatar_normal.jpg","source":"&lt;a href=&quot;http://twitterfeed.com&quot; rel=&quot;nofollow&quot;&gt;twitterfeed&lt;/a&gt;","text":"Must be a Jimmy Chew shoe: Remember, always thoroughly chew your food. It\u2019s better for your digestiv... http://t.co/p8QX3iX2 #cute #pets","to_user_id":null,"to_user_id_str":null},{"created_at":"Sun, 18 Sep 2011 16:53:50 +0000","from_user":"UptownCloset","from_user_id":105071600,"from_user_id_str":"105071600","geo":null,"id":115468582581829632,"id_str":"115468582581829632","iso_language_code":"en","metadata":{"result_type":"recent"},"profile_image_url":"http://a2.twimg.com/profile_images/776068042/Shopping20Logo20TSS_normal.jpg","source":"&lt;a href=&quot;http://twitterfeed.com&quot; rel=&quot;nofollow&quot;&gt;twitterfeed&lt;/a&gt;","text":"Must be a Jimmy Chew shoe: Remember, always thoroughly chew your food. It\u2019s better for your digestive system.\n\nC... http://t.co/5nKS0JYh","to_user_id":null,"to_user_id_str":null},{"created_at":"Sun, 18 Sep 2011 16:53:49 +0000","from_user":"KawaiiFriends","from_user_id":82117293,"from_user_id_str":"82117293","geo":null,"id":115468582313402369,"id_str":"115468582313402369","iso_language_code":"en","metadata":{"result_type":"recent"},"profile_image_url":"http://a1.twimg.com/profile_images/557255464/tco-avatar_normal.jpg","source":"&lt;a href=&quot;http://twitterfeed.com&quot; rel=&quot;nofollow&quot;&gt;twitterfeed&lt;/a&gt;","text":"Cute Overload Post! Must be a Jimmy Chew shoe: Remember, always thoroughly chew your food. I... http://t.co/Z4I0k7Pv #cuteoverload #cute","to_user_id":null,"to_user_id_str":null},{"created_at":"Sun, 18 Sep 2011 16:53:49 +0000","from_user":"lolcute","from_user_id":6554815,"from_user_id_str":"6554815","geo":null,"id":115468581831053312,"id_str":"115468581831053312","iso_language_code":"en","metadata":{"result_type":"recent"},"profile_image_url":"http://a1.twimg.com/profile_images/91106120/sleep-in-bowl_normal.png","source":"&lt;a href=&quot;http://twitterfeed.com&quot; rel=&quot;nofollow&quot;&gt;twitterfeed&lt;/a&gt;","text":"Must be a Jimmy Chew shoe http://t.co/Ugdghoim","to_user_id":null,"to_user_id_str":null},{"created_at":"Sun, 18 Sep 2011 16:53:49 +0000","from_user":"cindyb37","from_user_id":10381437,"from_user_id_str":"10381437","geo":null,"id":115468581789114368,"id_str":"115468581789114368","iso_language_code":"en","metadata":{"result_type":"recent"},"profile_image_url":"http://a2.twimg.com/profile_images/126063548/l_e152656fe6fd4e9182b4ebaca5358a86_normal.jpg","source":"&lt;a href=&quot;http://twitterfeed.com&quot; rel=&quot;nofollow&quot;&gt;twitterfeed&lt;/a&gt;","text":"Must be a Jimmy Chew shoe http://t.co/cFdtQv3R","to_user_id":null,"to_user_id_str":null},{"created_at":"Sun, 18 Sep 2011 16:53:41 +0000","from_user":"rati_wannapanop","from_user_id":167371020,"from_user_id_str":"167371020","geo":null,"id":115468546779254784,"id_str":"115468546779254784","iso_language_code":"en","metadata":{"result_type":"recent"},"profile_image_url":"http://a0.twimg.com/sticky/default_profile_images/default_profile_5_normal.png","source":"&lt;a href=&quot;http://www.google.com/&quot; rel=&quot;nofollow&quot;&gt;Google&lt;/a&gt;","text":"Must be a Jimmy Chew shoe http://t.co/8nMKwbne","to_user_id":null,"to_user_id_str":null},{"created_at":"Sun, 18 Sep 2011 16:51:01 +0000","from_user":"TeresaMilligan","from_user_id":7061088,"from_user_id_str":"7061088","geo":null,"id":115467875082448896,"id_str":"115467875082448896","iso_language_code":"en","metadata":{"result_type":"recent"},"profile_image_url":"http://a0.twimg.com/profile_images/1410713328/profile_normal.jpg","source":"&lt;a href=&quot;http://publicize.wp.com/&quot; rel=&quot;nofollow&quot;&gt;WordPress.com&lt;/a&gt;","text":"RT @CuteOverload: You Will Melt Nao http://t.co/n5c0Bcnx","to_user_id":null,"to_user_id_str":null},{"created_at":"Sun, 18 Sep 2011 16:42:01 +0000","from_user":"KR1S713","from_user_id":160875142,"from_user_id_str":"160875142","geo":null,"id":115465612381257728,"id_str":"115465612381257728","iso_language_code":"en","metadata":{"result_type":"recent"},"profile_image_url":"http://a2.twimg.com/profile_images/1178079271/wine_normal.jpg","source":"&lt;a href=&quot;http://publicize.wp.com/&quot; rel=&quot;nofollow&quot;&gt;WordPress.com&lt;/a&gt;","text":"RT @CuteOverload: It's Caturday Night so I brought the Glow Kitten http://t.co/Surn6uCP","to_user_id":null,"to_user_id_str":null},{"created_at":"Sun, 18 Sep 2011 15:56:08 +0000","from_user":"MyFavPupJasmine","from_user_id":233494742,"from_user_id_str":"233494742","geo":null,"id":115454065307160576,"id_str":"115454065307160576","iso_language_code":"en","metadata":{"result_type":"recent"},"profile_image_url":"http://a0.twimg.com/profile_images/1249083119/YT_JAZ_normal.JPG","source":"&lt;a href=&quot;http://twitter.com/tweetbutton&quot; rel=&quot;nofollow&quot;&gt;Tweet Button&lt;/a&gt;","text":"Just gotta pick up a few things at #Target http://t.co/eqbZvmt0 /via @wordpressdotcom #shopping #dog has a video! http://t.co/p9GWWRXs","to_user_id":null,"to_user_id_str":null},{"created_at":"Sun, 18 Sep 2011 15:46:43 +0000","from_user":"MyFavPupJasmine","from_user_id":233494742,"from_user_id_str":"233494742","geo":null,"id":115451692073500672,"id_str":"115451692073500672","iso_language_code":"en","metadata":{"result_type":"recent"},"profile_image_url":"http://a0.twimg.com/profile_images/1249083119/YT_JAZ_normal.JPG","source":"&lt;a href=&quot;http://twitter.com/tweetbutton&quot; rel=&quot;nofollow&quot;&gt;Tweet Button&lt;/a&gt;","text":"Jaz is on Cuteoverload.com!!!   :D   :D   :D   http://t.co/eqbZvmt0 /via @wordpressdotcom  #cutedog #shopping","to_user_id":null,"to_user_id_str":null},{"created_at":"Sun, 18 Sep 2011 15:00:06 +0000","from_user":"tallulahsmom","from_user_id":20545761,"from_user_id_str":"20545761","geo":null,"id":115439963096621056,"id_str":"115439963096621056","iso_language_code":"en","metadata":{"result_type":"recent"},"profile_image_url":"http://a0.twimg.com/profile_images/1544886437/Tallulah_as_Mario_normal.jpg","source":"&lt;a href=&quot;http://twitter.com/tweetbutton&quot; rel=&quot;nofollow&quot;&gt;Tweet Button&lt;/a&gt;","text":"You've Gone Too Far, George Lucas http://t.co/ZayUqBQ2 /via @wordpressdotcom / Kittens!!","to_user_id":null,"to_user_id_str":null},{"created_at":"Sun, 18 Sep 2011 14:53:00 +0000","from_user":"morganelisa","from_user_id":112752597,"from_user_id_str":"112752597","geo":null,"id":115438175559757824,"id_str":"115438175559757824","iso_language_code":"en","metadata":{"result_type":"recent"},"profile_image_url":"http://a0.twimg.com/profile_images/854429403/1_normal.jpg","source":"&lt;a href=&quot;http://twitter.com/devices&quot; rel=&quot;nofollow&quot;&gt;txt&lt;/a&gt;","text":"@alexalyse hahaha that sounds like cuteoverload.com dont ever go to the site though, you'll never leave","to_user":"AlexAlyse","to_user_id":112300076,"to_user_id_str":"112300076"},{"created_at":"Sun, 18 Sep 2011 13:27:14 +0000","from_user":"hufflepants","from_user_id":1514844,"from_user_id_str":"1514844","geo":null,"id":115416593017749504,"id_str":"115416593017749504","iso_language_code":"en","metadata":{"result_type":"recent"},"profile_image_url":"http://a3.twimg.com/profile_images/1509134426/me_n_501_normal.jpg","source":"&lt;a href=&quot;http://www.alphonsolabs.com/&quot; rel=&quot;nofollow&quot;&gt;Pulse News&lt;/a&gt;","text":"The end of feline AIDS? | It\u2019s Caturday Night so I brought the Glow Kitten http://t.co/t1l7ALr1","to_user_id":null,"to_user_id_str":null},{"created_at":"Sun, 18 Sep 2011 13:09:09 +0000","from_user":"xfl2","from_user_id":178185538,"from_user_id_str":"178185538","geo":null,"id":115412039152828416,"id_str":"115412039152828416","iso_language_code":"en","metadata":{"result_type":"recent"},"profile_image_url":"http://a2.twimg.com/sticky/default_profile_images/default_profile_3_normal.png","source":"&lt;a href=&quot;http://www.flipboard.com&quot; rel=&quot;nofollow&quot;&gt;Flipboard&lt;/a&gt;","text":"http://t.co/kkF50q1B","to_user_id":null,"to_user_id_str":null},{"created_at":"Sun, 18 Sep 2011 11:33:22 +0000","from_user":"surfingann","from_user_id":49856641,"from_user_id_str":"49856641","geo":null,"id":115387938325544961,"id_str":"115387938325544961","iso_language_code":"en","metadata":{"result_type":"recent"},"profile_image_url":"http://a0.twimg.com/profile_images/1324944336/IMGP01052_normal.jpg","source":"&lt;a href=&quot;http://twitter.com/tweetbutton&quot; rel=&quot;nofollow&quot;&gt;Tweet Button&lt;/a&gt;","text":"It's Caturday Night so I brought the Glow Kitten http://t.co/tkR8T77g /via @wordpressdotcom","to_user_id":null,"to_user_id_str":null},{"created_at":"Sun, 18 Sep 2011 11:33:02 +0000","from_user":"surfingann","from_user_id":49856641,"from_user_id_str":"49856641","geo":null,"id":115387850681352192,"id_str":"115387850681352192","iso_language_code":"en","metadata":{"result_type":"recent"},"profile_image_url":"http://a0.twimg.com/profile_images/1324944336/IMGP01052_normal.jpg","source":"&lt;a href=&quot;http://twitter.com/tweetbutton&quot; rel=&quot;nofollow&quot;&gt;Tweet Button&lt;/a&gt;","text":"This background TOTALLY distracts from my cuteness. http://t.co/VkTvvqv0 /via @wordpressdotcom","to_user_id":null,"to_user_id_str":null},{"created_at":"Sun, 18 Sep 2011 11:32:32 +0000","from_user":"surfingann","from_user_id":49856641,"from_user_id_str":"49856641","geo":null,"id":115387728488710144,"id_str":"115387728488710144","iso_language_code":"en","metadata":{"result_type":"recent"},"profile_image_url":"http://a0.twimg.com/profile_images/1324944336/IMGP01052_normal.jpg","source":"&lt;a href=&quot;http://twitter.com/tweetbutton&quot; rel=&quot;nofollow&quot;&gt;Tweet Button&lt;/a&gt;","text":"LOLpug = Little Old Lady Pug http://t.co/WPMZQoed /via @wordpressdotcom","to_user_id":null,"to_user_id_str":null},{"created_at":"Sun, 18 Sep 2011 11:32:24 +0000","from_user":"deborahkerr","from_user_id":5477382,"from_user_id_str":"5477382","geo":null,"id":115387692493180928,"id_str":"115387692493180928","iso_language_code":"en","metadata":{"result_type":"recent"},"profile_image_url":"http://a2.twimg.com/profile_images/1492627706/image_normal.jpg","source":"&lt;a href=&quot;http://publicize.wp.com/&quot; rel=&quot;nofollow&quot;&gt;WordPress.com&lt;/a&gt;","text":"RT @CuteOverload: It's Caturday Night so I brought the Glow Kitten http://t.co/Surn6uCP","to_user_id":null,"to_user_id_str":null},{"created_at":"Sun, 18 Sep 2011 11:30:34 +0000","from_user":"surfingann","from_user_id":49856641,"from_user_id_str":"49856641","geo":null,"id":115387232310931456,"id_str":"115387232310931456","iso_language_code":"en","metadata":{"result_type":"recent"},"profile_image_url":"http://a0.twimg.com/profile_images/1324944336/IMGP01052_normal.jpg","source":"&lt;a href=&quot;http://twitter.com/tweetbutton&quot; rel=&quot;nofollow&quot;&gt;Tweet Button&lt;/a&gt;","text":"Only They Know For Sure http://t.co/egktYUYo /via @wordpressdotcom","to_user_id":null,"to_user_id_str":null},{"created_at":"Sun, 18 Sep 2011 11:29:43 +0000","from_user":"Pet_Hooligans","from_user_id":28834549,"from_user_id_str":"28834549","geo":null,"id":115387017814224896,"id_str":"115387017814224896","iso_language_code":"en","metadata":{"result_type":"recent"},"profile_image_url":"http://a1.twimg.com/profile_images/1500632400/pethooligan_normal.png","source":"&lt;a href=&quot;http://www.facebook.com/twitter&quot; rel=&quot;nofollow&quot;&gt;Facebook&lt;/a&gt;","text":"He's right you know.... http://t.co/k80WWdjo","to_user_id":null,"to_user_id_str":null},{"created_at":"Sun, 18 Sep 2011 10:26:17 +0000","from_user":"rosie_braye","from_user_id":406579746,"from_user_id_str":"406579746","geo":null,"id":115371055455019009,"id_str":"115371055455019009","iso_language_code":"en","metadata":{"result_type":"recent"},"profile_image_url":"http://a0.twimg.com/profile_images/1540628450/227218_10150174226647291_619592290_6968620_2365017_n_normal.jpg","source":"&lt;a href=&quot;http://www.htc.com&quot; rel=&quot;nofollow&quot;&gt;  HTC Peep&lt;/a&gt;","text":"Aww, nooo, don't cry kitteh! RT @CuteOverload You Will Melt Nao http://t.co/OiPn6Xbb","to_user_id":null,"to_user_id_str":null},{"created_at":"Sun, 18 Sep 2011 09:53:15 +0000","from_user":"othernine","from_user_id":198091,"from_user_id_str":"198091","geo":null,"id":115362740587077632,"id_str":"115362740587077632","iso_language_code":"en","metadata":{"result_type":"recent"},"profile_image_url":"http://a2.twimg.com/profile_images/1461840076/image_normal.jpg","source":"&lt;a href=&quot;http://reederapp.com&quot; rel=&quot;nofollow&quot;&gt;Reeder&lt;/a&gt;","text":"Just gotta pick up a few things at Target http://j.mp/nOuiWs","to_user_id":null,"to_user_id_str":null},{"created_at":"Sun, 18 Sep 2011 09:52:47 +0000","from_user":"shoshonasnow","from_user_id":8465125,"from_user_id_str":"8465125","geo":null,"id":115362625331806209,"id_str":"115362625331806209","iso_language_code":"en","metadata":{"result_type":"recent"},"profile_image_url":"http://a2.twimg.com/profile_images/323657154/upload_twitter_normal.jpg","source":"&lt;a href=&quot;http://levelupstudio.com&quot; rel=&quot;nofollow&quot;&gt;Plume\u00A0\u00A0&lt;/a&gt;","text":"http://t.co/mfLsMCmp","to_user_id":null,"to_user_id_str":null},{"created_at":"Sun, 18 Sep 2011 07:03:02 +0000","from_user":"vivienmah","from_user_id":15457404,"from_user_id_str":"15457404","geo":null,"id":115319904126779392,"id_str":"115319904126779392","iso_language_code":"en","metadata":{"result_type":"recent"},"profile_image_url":"http://a3.twimg.com/profile_images/1301903980/photo__9__normal.JPG","source":"&lt;a href=&quot;http://publicize.wp.com/&quot; rel=&quot;nofollow&quot;&gt;WordPress.com&lt;/a&gt;","text":"RT @CuteOverload: Ladies and Gentlemen, The #CutestKittenintheWorld http://t.co/FHZ0z3V","to_user_id":null,"to_user_id_str":null},{"created_at":"Sun, 18 Sep 2011 06:55:46 +0000","from_user":"tweetheart4711","from_user_id":85817985,"from_user_id_str":"85817985","geo":null,"id":115318077855502336,"id_str":"115318077855502336","iso_language_code":"en","metadata":{"result_type":"recent"},"profile_image_url":"http://a1.twimg.com/profile_images/1191265939/Horse_Guards_Parade_normal.jpg","source":"&lt;a href=&quot;http://twitter.com/&quot;&gt;web&lt;/a&gt;","text":"Icons of cute in fur &amp; feather: http://t.co/Bv7bbpDN http://t.co/iuX0xjDC #shareonSunday 'cos they're sooooo cute!","to_user_id":null,"to_user_id_str":null},{"created_at":"Sun, 18 Sep 2011 04:33:54 +0000","from_user":"patdkitten","from_user_id":245948368,"from_user_id_str":"245948368","geo":null,"id":115282374748672000,"id_str":"115282374748672000","iso_language_code":"en","metadata":{"result_type":"recent"},"profile_image_url":"http://a0.twimg.com/profile_images/1266566985/Picture_6_normal.jpg","source":"&lt;a href=&quot;http://twitter.com/tweetbutton&quot; rel=&quot;nofollow&quot;&gt;Tweet Button&lt;/a&gt;","text":"You've Gone Too Far, George Lucas http://t.co/t5xFLl1Y /via @wordpressdotcom","to_user_id":null,"to_user_id_str":null},{"created_at":"Sun, 18 Sep 2011 04:19:58 +0000","from_user":"S_Delancey","from_user_id":259663059,"from_user_id_str":"259663059","geo":null,"id":115278866339201024,"id_str":"115278866339201024","iso_language_code":"en","metadata":{"result_type":"recent"},"profile_image_url":"http://a2.twimg.com/profile_images/1296305481/domoPumpkin_normal.jpg","source":"&lt;a href=&quot;http://twitterfeed.com&quot; rel=&quot;nofollow&quot;&gt;twitterfeed&lt;/a&gt;","text":"It\u2019s Caturday Night so I brought the Glow Kitten: [Techno music blasting]\nAnyone have any Ecstasy?\n\nBut seriousl... http://t.co/JcSLWkQM","to_user_id":null,"to_user_id_str":null},{"created_at":"Sun, 18 Sep 2011 04:08:51 +0000","from_user":"kalla_lily","from_user_id":1095024,"from_user_id_str":"1095024","geo":null,"id":115276069204000768,"id_str":"115276069204000768","iso_language_code":"en","metadata":{"result_type":"recent"},"profile_image_url":"http://a2.twimg.com/profile_images/1415636418/hordekitty_normal.PNG","source":"&lt;a href=&quot;http://publicize.wp.com/&quot; rel=&quot;nofollow&quot;&gt;WordPress.com&lt;/a&gt;","text":"RT @CuteOverload: It's Caturday Night so I brought the Glow Kitten http://t.co/Surn6uCP","to_user_id":null,"to_user_id_str":null},{"created_at":"Sun, 18 Sep 2011 04:03:25 +0000","from_user":"rensrambles","from_user_id":251495376,"from_user_id_str":"251495376","geo":null,"id":115274702343249921,"id_str":"115274702343249921","iso_language_code":"en","metadata":{"result_type":"recent"},"profile_image_url":"http://a1.twimg.com/profile_images/1380461642/Best_Profile_normal.jpg","source":"&lt;a href=&quot;http://twitter.com/&quot;&gt;web&lt;/a&gt;","text":"@imabookshark Okay, one more for the road. I have to since you mentioned exercise... http://t.co/TMRZFkbm","to_user":"imabookshark","to_user_id":263762540,"to_user_id_str":"263762540"},{"created_at":"Sun, 18 Sep 2011 03:30:10 +0000","from_user":"paix120_feeds","from_user_id":5335452,"from_user_id_str":"5335452","geo":null,"id":115266333658193920,"id_str":"115266333658193920","iso_language_code":"en","metadata":{"result_type":"recent"},"profile_image_url":"http://a1.twimg.com/profile_images/81524842/Renee_Icon_purple_normal.jpg","source":"&lt;a href=&quot;http://twitterfeed.com&quot; rel=&quot;nofollow&quot;&gt;twitterfeed&lt;/a&gt;","text":"Reading: It\u2019s Caturday Night so I brought the Glow Kitten: [Techno music blasting]\nAnyone have any Ecstasy?\n\nBut... http://t.co/bu1cJFVS","to_user_id":null,"to_user_id_str":null},{"created_at":"Sun, 18 Sep 2011 03:29:42 +0000","from_user":"Laughlovelive53","from_user_id":9017132,"from_user_id_str":"9017132","geo":null,"id":115266218583277568,"id_str":"115266218583277568","iso_language_code":"en","metadata":{"result_type":"recent"},"profile_image_url":"http://a2.twimg.com/profile_images/1517932535/image_normal.jpg","source":"&lt;a href=&quot;http://publicize.wp.com/&quot; rel=&quot;nofollow&quot;&gt;WordPress.com&lt;/a&gt;","text":"RT @CuteOverload: It's Caturday Night so I brought the Glow Kitten http://t.co/Surn6uCP","to_user_id":null,"to_user_id_str":null},{"created_at":"Sun, 18 Sep 2011 03:21:26 +0000","from_user":"Estanil_weavr","from_user_id":292281321,"from_user_id_str":"292281321","geo":null,"id":115264135628996608,"id_str":"115264135628996608","iso_language_code":"en","metadata":{"result_type":"recent"},"profile_image_url":"http://a3.twimg.com/profile_images/1424989830/avatar_normal","source":"&lt;a href=&quot;http://twitter.com/#!/download/iphone&quot; rel=&quot;nofollow&quot;&gt;Twitter for iPhone&lt;/a&gt;","text":"RT @VireoVideo: \u201C@CuteOverload  RE the Glow Kitten http://t.co/9Ztvs9ni\u201D Disgusting perversion of #science &amp; #nature \nWTF is wrong w U? #GE #Frankenpets","to_user_id":null,"to_user_id_str":null},{"created_at":"Sun, 18 Sep 2011 03:19:28 +0000","from_user":"VireoVideo","from_user_id":367731787,"from_user_id_str":"367731787","geo":null,"id":115263644064948224,"id_str":"115263644064948224","iso_language_code":"en","metadata":{"result_type":"recent"},"profile_image_url":"http://a2.twimg.com/profile_images/1546552703/image_normal.jpg","source":"&lt;a href=&quot;http://twitter.com/#!/download/iphone&quot; rel=&quot;nofollow&quot;&gt;Twitter for iPhone&lt;/a&gt;","text":"\u201C@CuteOverload  RE the Glow Kitten http://t.co/9Ztvs9ni\u201D Disgusting perversion of #science &amp; #nature \nWTF is wrong w U? #GE #Frankenpets","to_user_id":null,"to_user_id_str":null},{"created_at":"Sun, 18 Sep 2011 03:17:17 +0000","from_user":"anngregory74","from_user_id":1028641,"from_user_id_str":"1028641","geo":null,"id":115263091184373761,"id_str":"115263091184373761","iso_language_code":"en","metadata":{"result_type":"recent"},"profile_image_url":"http://a2.twimg.com/profile_images/1169074025/image_normal.jpg","source":"&lt;a href=&quot;http://publicize.wp.com/&quot; rel=&quot;nofollow&quot;&gt;WordPress.com&lt;/a&gt;","text":"RT @CuteOverload: It's Caturday Night so I brought the Glow Kitten http://t.co/Surn6uCP","to_user_id":null,"to_user_id_str":null},{"created_at":"Sun, 18 Sep 2011 02:44:51 +0000","from_user":"chloemcgill","from_user_id":117509280,"from_user_id_str":"117509280","geo":null,"id":115254932055142400,"id_str":"115254932055142400","iso_language_code":"en","metadata":{"result_type":"recent"},"profile_image_url":"http://a1.twimg.com/profile_images/1152153353/frog_normal.jpg","source":"&lt;a href=&quot;http://www.feedblitz.com/f/f.fbz?help/default#twitter&quot; rel=&quot;nofollow&quot;&gt;FeedBlitz&lt;/a&gt;","text":"It's Caturday Night so I brought the Glow Kitten via Cute Overload - [Techno music blasting] Anyone have ... http://t.co/50AZ4R6B","to_user_id":null,"to_user_id_str":null},{"created_at":"Sun, 18 Sep 2011 02:30:02 +0000","from_user":"MyFavPupJasmine","from_user_id":233494742,"from_user_id_str":"233494742","geo":null,"id":115251203012706304,"id_str":"115251203012706304","iso_language_code":"en","metadata":{"result_type":"recent"},"profile_image_url":"http://a0.twimg.com/profile_images/1249083119/YT_JAZ_normal.JPG","source":"&lt;a href=&quot;http://publicize.wp.com/&quot; rel=&quot;nofollow&quot;&gt;WordPress.com&lt;/a&gt;","text":"RT @CuteOverload: Just gotta pick up a few things at #Target: http://t.co/4QVK6S2n","to_user_id":null,"to_user_id_str":null},{"created_at":"Sun, 18 Sep 2011 02:29:11 +0000","from_user":"tripleoverload","from_user_id":571463,"from_user_id_str":"571463","geo":null,"id":115250989690392578,"id_str":"115250989690392578","iso_language_code":"en","metadata":{"result_type":"recent"},"profile_image_url":"http://a1.twimg.com/profile_images/28458812/baru_1_normal.jpg","source":"&lt;a href=&quot;http://twitterfeed.com&quot; rel=&quot;nofollow&quot;&gt;twitterfeed&lt;/a&gt;","text":"[cute*] It\u2019s Caturday Night so I brought the Glow Kitten http://t.co/CncydKFm","to_user_id":null,"to_user_id_str":null},{"created_at":"Sun, 18 Sep 2011 02:23:39 +0000","from_user":"LearnSales","from_user_id":262492423,"from_user_id_str":"262492423","geo":null,"id":115249593771491328,"id_str":"115249593771491328","iso_language_code":"en","metadata":{"result_type":"recent"},"profile_image_url":"http://a2.twimg.com/profile_images/1309943199/30154_518077057863_60201317_30666749_8187519_n_normal.jpg","source":"&lt;a href=&quot;http://twitterfeed.com&quot; rel=&quot;nofollow&quot;&gt;twitterfeed&lt;/a&gt;","text":"It\u2019s Caturday Night so I brought the Glow Kitten http://t.co/N1Ki2pIc","to_user_id":null,"to_user_id_str":null},{"created_at":"Sun, 18 Sep 2011 02:20:23 +0000","from_user":"2dogtrail","from_user_id":13301221,"from_user_id_str":"13301221","geo":null,"id":115248774875590656,"id_str":"115248774875590656","iso_language_code":"en","metadata":{"result_type":"recent"},"profile_image_url":"http://a1.twimg.com/profile_images/1417655843/Mary_and_2_Dogs_retouched_normal.jpg","source":"&lt;a href=&quot;http://twitter.com/tweetbutton&quot; rel=&quot;nofollow&quot;&gt;Tweet Button&lt;/a&gt;","text":"Just gotta pick up a few things at Target http://t.co/HXQicyQ1 /via @wordpressdotcom","to_user_id":null,"to_user_id_str":null},{"created_at":"Sun, 18 Sep 2011 02:19:30 +0000","from_user":"MyFavPupJasmine","from_user_id":233494742,"from_user_id_str":"233494742","geo":null,"id":115248551554064384,"id_str":"115248551554064384","iso_language_code":"en","metadata":{"result_type":"recent"},"profile_image_url":"http://a0.twimg.com/profile_images/1249083119/YT_JAZ_normal.JPG","source":"&lt;a href=&quot;http://twitter.com/tweetbutton&quot; rel=&quot;nofollow&quot;&gt;Tweet Button&lt;/a&gt;","text":"Guess who's favorite pup just got featured on CuteOverload.com!?  =D  (OK- it's Jaz!)  \n http://t.co/eqbZvmt0 /via @wordpressdotcom #cutedog","to_user_id":null,"to_user_id_str":null},{"created_at":"Sun, 18 Sep 2011 02:17:34 +0000","from_user":"BarnestormJohn","from_user_id":239133333,"from_user_id_str":"239133333","geo":null,"id":115248065782362112,"id_str":"115248065782362112","iso_language_code":"en","metadata":{"result_type":"recent"},"profile_image_url":"http://a0.twimg.com/profile_images/1194649775/johnr_normal.JPG","source":"&lt;a href=&quot;http://blackberry.com/twitter&quot; rel=&quot;nofollow&quot;&gt;Twitter for BlackBerry\u00AE&lt;/a&gt;","text":"Mayo Clinic gene experiment Glow Cat - &quot;@CuteOverload: It's Caturday Night so I brought the Glow Kitten http://t.co/7FoFz6ox&quot;","to_user_id":null,"to_user_id_str":null},{"created_at":"Sun, 18 Sep 2011 02:15:11 +0000","from_user":"rati_wannapanop","from_user_id":167371020,"from_user_id_str":"167371020","geo":null,"id":115247464684064769,"id_str":"115247464684064769","iso_language_code":"en","metadata":{"result_type":"recent"},"profile_image_url":"http://a0.twimg.com/sticky/default_profile_images/default_profile_5_normal.png","source":"&lt;a href=&quot;http://www.google.com/&quot; rel=&quot;nofollow&quot;&gt;Google&lt;/a&gt;","text":"It\u2019s Caturday Night so I brought the Glow Kitten http://t.co/SLTiBciD","to_user_id":null,"to_user_id_str":null},{"created_at":"Sun, 18 Sep 2011 02:14:29 +0000","from_user":"aMMykoro","from_user_id":132697621,"from_user_id_str":"132697621","geo":null,"id":115247286879137793,"id_str":"115247286879137793","iso_language_code":"en","metadata":{"result_type":"recent"},"profile_image_url":"http://a2.twimg.com/profile_images/1537063817/Copy_of_63_normal.jpg","source":"&lt;a href=&quot;http://blackberry.com/twitter&quot; rel=&quot;nofollow&quot;&gt;Twitter for BlackBerry\u00AE&lt;/a&gt;","text":"Read this @ktaj0303 !! RT @CuteOverload: It's Caturday Night so I brought the Glow Kitten http://t.co/tMwpVckA","to_user_id":null,"to_user_id_str":null},{"created_at":"Sun, 18 Sep 2011 02:12:35 +0000","from_user":"RakhaSN","from_user_id":395769744,"from_user_id_str":"395769744","geo":null,"id":115246811731595266,"id_str":"115246811731595266","iso_language_code":"en","metadata":{"result_type":"recent"},"profile_image_url":"http://a3.twimg.com/profile_images/1506232602/313165_267454843264797_100000008494660_1153381_7258134_n_normal.jpg","source":"&lt;a href=&quot;http://twitterfeed.com&quot; rel=&quot;nofollow&quot;&gt;twitterfeed&lt;/a&gt;","text":"It\u2019s Caturday Night so I brought the Glow Kitten: [Techno music blasting]\nAnyone have any Ecstasy?\n\nBut seriousl... http://t.co/f0BKykZC","to_user_id":null,"to_user_id_str":null},{"created_at":"Sun, 18 Sep 2011 02:12:35 +0000","from_user":"AmandaBosten","from_user_id":366365277,"from_user_id_str":"366365277","geo":null,"id":115246811643518976,"id_str":"115246811643518976","iso_language_code":"en","metadata":{"result_type":"recent"},"profile_image_url":"http://a0.twimg.com/profile_images/1453901349/p3ihy_normal.jpg","source":"&lt;a href=&quot;http://twitterfeed.com&quot; rel=&quot;nofollow&quot;&gt;twitterfeed&lt;/a&gt;","text":"It\u2019s Caturday Night so I brought the Glow Kitten: [Techno music blasting]\nAnyone have any Ecstasy?\n\nBut seriousl... http://t.co/R5dJKvDD","to_user_id":null,"to_user_id_str":null},{"created_at":"Sun, 18 Sep 2011 02:12:35 +0000","from_user":"UptownCloset","from_user_id":105071600,"from_user_id_str":"105071600","geo":null,"id":115246810930495488,"id_str":"115246810930495488","iso_language_code":"en","metadata":{"result_type":"recent"},"profile_image_url":"http://a2.twimg.com/profile_images/776068042/Shopping20Logo20TSS_normal.jpg","source":"&lt;a href=&quot;http://twitterfeed.com&quot; rel=&quot;nofollow&quot;&gt;twitterfeed&lt;/a&gt;","text":"It\u2019s Caturday Night so I brought the Glow Kitten: [Techno music blasting]\nAnyone have any Ecstasy?\n\nBut seriousl... http://t.co/GXpd3sat","to_user_id":null,"to_user_id_str":null},{"created_at":"Sun, 18 Sep 2011 02:12:35 +0000","from_user":"KawaiiFriends","from_user_id":82117293,"from_user_id_str":"82117293","geo":null,"id":115246810540421121,"id_str":"115246810540421121","iso_language_code":"en","metadata":{"result_type":"recent"},"profile_image_url":"http://a1.twimg.com/profile_images/557255464/tco-avatar_normal.jpg","source":"&lt;a href=&quot;http://twitterfeed.com&quot; rel=&quot;nofollow&quot;&gt;twitterfeed&lt;/a&gt;","text":"Cute Overload Post! It\u2019s Caturday Night so I brought the Glow Kitten: [Techno music blasting... http://t.co/ZhViASRa #cuteoverload #cute","to_user_id":null,"to_user_id_str":null},{"created_at":"Sun, 18 Sep 2011 02:12:35 +0000","from_user":"cindyb37","from_user_id":10381437,"from_user_id_str":"10381437","geo":null,"id":115246810271981568,"id_str":"115246810271981568","iso_language_code":"en","metadata":{"result_type":"recent"},"profile_image_url":"http://a2.twimg.com/profile_images/126063548/l_e152656fe6fd4e9182b4ebaca5358a86_normal.jpg","source":"&lt;a href=&quot;http://twitterfeed.com&quot; rel=&quot;nofollow&quot;&gt;twitterfeed&lt;/a&gt;","text":"It\u2019s Caturday Night so I brought the Glow Kitten http://t.co/LEMiSRzY","to_user_id":null,"to_user_id_str":null},{"created_at":"Sun, 18 Sep 2011 02:12:35 +0000","from_user":"lolcute","from_user_id":6554815,"from_user_id_str":"6554815","geo":null,"id":115246810267783168,"id_str":"115246810267783168","iso_language_code":"en","metadata":{"result_type":"recent"},"profile_image_url":"http://a1.twimg.com/profile_images/91106120/sleep-in-bowl_normal.png","source":"&lt;a href=&quot;http://twitterfeed.com&quot; rel=&quot;nofollow&quot;&gt;twitterfeed&lt;/a&gt;","text":"It\u2019s Caturday Night so I brought the Glow Kitten http://t.co/3cTpfdgc","to_user_id":null,"to_user_id_str":null},{"created_at":"Sun, 18 Sep 2011 02:11:38 +0000","from_user":"angyoung00","from_user_id":409433227,"from_user_id_str":"409433227","geo":null,"id":115246571897094144,"id_str":"115246571897094144","iso_language_code":"en","metadata":{"result_type":"recent"},"profile_image_url":"http://a1.twimg.com/profile_images/1551714015/troy_normal.jpg","source":"&lt;a href=&quot;http://publicize.wp.com/&quot; rel=&quot;nofollow&quot;&gt;WordPress.com&lt;/a&gt;","text":"RT @CuteOverload: It's Caturday Night so I brought the Glow Kitten http://t.co/Surn6uCP","to_user_id":null,"to_user_id_str":null},{"created_at":"Sun, 18 Sep 2011 02:11:00 +0000","from_user":"CuteOverload","from_user_id":692409,"from_user_id_str":"692409","geo":null,"id":115246410114404353,"id_str":"115246410114404353","iso_language_code":"en","metadata":{"result_type":"recent"},"profile_image_url":"http://a1.twimg.com/profile_images/97078327/co_normal.png","source":"&lt;a href=&quot;http://publicize.wp.com/&quot; rel=&quot;nofollow&quot;&gt;WordPress.com&lt;/a&gt;","text":"It's Caturday Night so I brought the Glow Kitten http://t.co/Surn6uCP","to_user_id":null,"to_user_id_str":null},{"created_at":"Sun, 18 Sep 2011 02:06:51 +0000","from_user":"flexibeast","from_user_id":60667789,"from_user_id_str":"60667789","geo":null,"id":115245369096544256,"id_str":"115245369096544256","iso_language_code":"en","metadata":{"result_type":"recent"},"profile_image_url":"http://a1.twimg.com/profile_images/503474129/thinking_rat_normal.jpg","source":"&lt;a href=&quot;http://twmode.sf.net/&quot; rel=&quot;nofollow&quot;&gt;twmode&lt;/a&gt;","text":"Kitteh Star Wars! http://t.co/XydhLhy9","to_user_id":null,"to_user_id_str":null},{"created_at":"Sun, 18 Sep 2011 02:05:31 +0000","from_user":"Cafe_Nirvana","from_user_id":128993304,"from_user_id_str":"128993304","geo":null,"id":115245033782919168,"id_str":"115245033782919168","iso_language_code":"en","metadata":{"result_type":"recent"},"profile_image_url":"http://a1.twimg.com/profile_images/1522097391/Temo_avatr_normal.jpg","source":"&lt;a href=&quot;http://twitter.com/tweetbutton&quot; rel=&quot;nofollow&quot;&gt;Tweet Button&lt;/a&gt;","text":"pupiieeee !!  squeeee!! ( ^.^ )   This background TOTALLY distracts from my cuteness. http://t.co/AWQT83w8 /via @cuteoverload","to_user_id":null,"to_user_id_str":null},{"created_at":"Sun, 18 Sep 2011 01:01:16 +0000","from_user":"rati_wannapanop","from_user_id":167371020,"from_user_id_str":"167371020","geo":null,"id":115228863633690624,"id_str":"115228863633690624","iso_language_code":"en","metadata":{"result_type":"recent"},"profile_image_url":"http://a0.twimg.com/sticky/default_profile_images/default_profile_5_normal.png","source":"&lt;a href=&quot;http://www.google.com/&quot; rel=&quot;nofollow&quot;&gt;Google&lt;/a&gt;","text":"This background TOTALLY distracts from my cuteness. http://t.co/eXPTDkUd","to_user_id":null,"to_user_id_str":null},{"created_at":"Sun, 18 Sep 2011 01:00:21 +0000","from_user":"vivienmah","from_user_id":15457404,"from_user_id_str":"15457404","geo":null,"id":115228630539436032,"id_str":"115228630539436032","iso_language_code":"en","metadata":{"result_type":"recent"},"profile_image_url":"http://a3.twimg.com/profile_images/1301903980/photo__9__normal.JPG","source":"&lt;a href=&quot;http://www.flipboard.com&quot; rel=&quot;nofollow&quot;&gt;Flipboard&lt;/a&gt;","text":"Hahaha! @thebreg @stephchng @crashdummylover RT @CuteOverload: You Will Melt Nao http://t.co/pBeCXuG7","to_user_id":null,"to_user_id_str":null},{"created_at":"Sun, 18 Sep 2011 00:56:15 +0000","from_user":"vonneybeth","from_user_id":108914055,"from_user_id_str":"108914055","geo":null,"id":115227600372236289,"id_str":"115227600372236289","iso_language_code":"en","metadata":{"result_type":"recent"},"profile_image_url":"http://a0.twimg.com/profile_images/1489286023/mpavi_normal.jpg","source":"&lt;a href=&quot;http://twitter.com/tweetbutton&quot; rel=&quot;nofollow&quot;&gt;Tweet Button&lt;/a&gt;","text":"Equal Rights for All Hams http://t.co/7PuGvpgm /via @wordpressdotcom","to_user_id":null,"to_user_id_str":null},{"created_at":"Sun, 18 Sep 2011 00:42:17 +0000","from_user":"misslindadee","from_user_id":12686564,"from_user_id_str":"12686564","geo":null,"id":115224084605972480,"id_str":"115224084605972480","iso_language_code":"en","metadata":{"result_type":"recent"},"profile_image_url":"http://a0.twimg.com/profile_images/740355802/l2.a_normal.jpg","source":"&lt;a href=&quot;http://bit.ly&quot; rel=&quot;nofollow&quot;&gt;bitly&lt;/a&gt;","text":"Only They Know For Sure \u2014 Cute Overload http://t.co/ltoyGhj3","to_user_id":null,"to_user_id_str":null},{"created_at":"Sun, 18 Sep 2011 00:38:47 +0000","from_user":"tempestpilot","from_user_id":188676641,"from_user_id_str":"188676641","geo":null,"id":115223205068816384,"id_str":"115223205068816384","iso_language_code":"en","metadata":{"result_type":"recent"},"profile_image_url":"http://a3.twimg.com/profile_images/1180456454/tiny_normal.JPG","source":"&lt;a href=&quot;http://twitter.com/tweetbutton&quot; rel=&quot;nofollow&quot;&gt;Tweet Button&lt;/a&gt;","text":"Kitten wars. http://t.co/MbNpM7M6 /via","to_user_id":null,"to_user_id_str":null},{"created_at":"Sun, 18 Sep 2011 00:19:43 +0000","from_user":"chloemcgill","from_user_id":117509280,"from_user_id_str":"117509280","geo":null,"id":115218406881509376,"id_str":"115218406881509376","iso_language_code":"en","metadata":{"result_type":"recent"},"profile_image_url":"http://a1.twimg.com/profile_images/1152153353/frog_normal.jpg","source":"&lt;a href=&quot;http://www.feedblitz.com/f/f.fbz?help/default#twitter&quot; rel=&quot;nofollow&quot;&gt;FeedBlitz&lt;/a&gt;","text":"This background TOTALLY distracts from my cuteness. via Cute Overload - Can you walk me over to the grass or ... http://t.co/5m0bVUKX","to_user_id":null,"to_user_id_str":null},{"created_at":"Sun, 18 Sep 2011 00:11:57 +0000","from_user":"armadill2010","from_user_id":360801627,"from_user_id_str":"360801627","geo":null,"id":115216453363445760,"id_str":"115216453363445760","iso_language_code":"en","metadata":{"result_type":"recent"},"profile_image_url":"http://a2.twimg.com/profile_images/1456707966/ProfilePhoto_normal.png","source":"&lt;a href=&quot;http://www.alphonsolabs.com/&quot; rel=&quot;nofollow&quot;&gt;Pulse News&lt;/a&gt;","text":"This background TOTALLY distracts from my cuteness. http://t.co/GEVxxo98","to_user_id":null,"to_user_id_str":null},{"created_at":"Sun, 18 Sep 2011 00:05:59 +0000","from_user":"fotogirl","from_user_id":581876,"from_user_id_str":"581876","geo":null,"id":115214950850494464,"id_str":"115214950850494464","iso_language_code":"en","metadata":{"result_type":"recent"},"profile_image_url":"http://a2.twimg.com/profile_images/438212891/Goat_normal.jpg","source":"&lt;a href=&quot;http://twitter.com/tweetbutton&quot; rel=&quot;nofollow&quot;&gt;Tweet Button&lt;/a&gt;","text":"You've Gone Too Far, George Lucas http://t.co/XzlJxqpY /  LOL!!!","to_user_id":null,"to_user_id_str":null},{"created_at":"Sat, 17 Sep 2011 23:50:51 +0000","from_user":"tripleoverload","from_user_id":571463,"from_user_id_str":"571463","geo":null,"id":115211141315170304,"id_str":"115211141315170304","iso_language_code":"en","metadata":{"result_type":"recent"},"profile_image_url":"http://a1.twimg.com/profile_images/28458812/baru_1_normal.jpg","source":"&lt;a href=&quot;http://twitterfeed.com&quot; rel=&quot;nofollow&quot;&gt;twitterfeed&lt;/a&gt;","text":"[cute*] This background TOTALLY distracts from my cuteness. http://t.co/uwIJlix1","to_user_id":null,"to_user_id_str":null},{"created_at":"Sat, 17 Sep 2011 23:49:04 +0000","from_user":"eweirdworld","from_user_id":66199583,"from_user_id_str":"66199583","geo":null,"id":115210692491100160,"id_str":"115210692491100160","iso_language_code":"en","metadata":{"result_type":"recent"},"profile_image_url":"http://a3.twimg.com/profile_images/1302439371/gravatar_normal.jpg","source":"&lt;a href=&quot;http://twitterfeed.com&quot; rel=&quot;nofollow&quot;&gt;twitterfeed&lt;/a&gt;","text":"This background TOTALLY distracts from my cuteness.: T-bone smile- he got explored\u2026 I guess coz he\u2019s... http://t.co/5Oi67Xwi #cute #pets","to_user_id":null,"to_user_id_str":null},{"created_at":"Sat, 17 Sep 2011 23:45:01 +0000","from_user":"LearnSales","from_user_id":262492423,"from_user_id_str":"262492423","geo":null,"id":115209675368181760,"id_str":"115209675368181760","iso_language_code":"en","metadata":{"result_type":"recent"},"profile_image_url":"http://a2.twimg.com/profile_images/1309943199/30154_518077057863_60201317_30666749_8187519_n_normal.jpg","source":"&lt;a href=&quot;http://twitterfeed.com&quot; rel=&quot;nofollow&quot;&gt;twitterfeed&lt;/a&gt;","text":"This background TOTALLY distracts from my cuteness. http://t.co/vJGClk5F","to_user_id":null,"to_user_id_str":null},{"created_at":"Sat, 17 Sep 2011 23:42:03 +0000","from_user":"RakhaSN","from_user_id":395769744,"from_user_id_str":"395769744","geo":null,"id":115208928962420737,"id_str":"115208928962420737","iso_language_code":"en","metadata":{"result_type":"recent"},"profile_image_url":"http://a3.twimg.com/profile_images/1506232602/313165_267454843264797_100000008494660_1153381_7258134_n_normal.jpg","source":"&lt;a href=&quot;http://twitterfeed.com&quot; rel=&quot;nofollow&quot;&gt;twitterfeed&lt;/a&gt;","text":"This background TOTALLY distracts from my cuteness.: \n\n\nT-bone smile- he got explored\u2026I guess coz he\u2019s so darn c... http://t.co/JOO3s9e7","to_user_id":null,"to_user_id_str":null},{"created_at":"Sat, 17 Sep 2011 23:42:03 +0000","from_user":"SanDiegoHaven","from_user_id":231127036,"from_user_id_str":"231127036","geo":null,"id":115208928941453312,"id_str":"115208928941453312","iso_language_code":"en","metadata":{"result_type":"recent"},"profile_image_url":"http://a0.twimg.com/profile_images/1235915786/163892_10150127191003478_677983477_7854339_7711930_n_normal.jpg","source":"&lt;a href=&quot;http://twitterfeed.com&quot; rel=&quot;nofollow&quot;&gt;twitterfeed&lt;/a&gt;","text":"This background TOTALLY distracts from my cuteness.: \n\n\nT-bone smile- he got explored\u2026I guess coz he\u2019s so darn c... http://t.co/xI41SCYt","to_user_id":null,"to_user_id_str":null},{"created_at":"Sat, 17 Sep 2011 23:42:03 +0000","from_user":"AmandaBosten","from_user_id":366365277,"from_user_id_str":"366365277","geo":null,"id":115208928819810304,"id_str":"115208928819810304","iso_language_code":"en","metadata":{"result_type":"recent"},"profile_image_url":"http://a0.twimg.com/profile_images/1453901349/p3ihy_normal.jpg","source":"&lt;a href=&quot;http://twitterfeed.com&quot; rel=&quot;nofollow&quot;&gt;twitterfeed&lt;/a&gt;","text":"This background TOTALLY distracts from my cuteness.: \n\n\nT-bone smile- he got explored\u2026I guess coz he\u2019s so darn c... http://t.co/QmX6YuDk","to_user_id":null,"to_user_id_str":null},{"created_at":"Sat, 17 Sep 2011 23:42:03 +0000","from_user":"HomeStudioArts","from_user_id":5393077,"from_user_id_str":"5393077","geo":null,"id":115208928647847936,"id_str":"115208928647847936","iso_language_code":"en","metadata":{"result_type":"recent"},"profile_image_url":"http://a1.twimg.com/profile_images/1288707532/il_fullxfull_normal.jpg","source":"&lt;a href=&quot;http://twitterfeed.com&quot; rel=&quot;nofollow&quot;&gt;twitterfeed&lt;/a&gt;","text":"This background TOTALLY distracts from my cuteness.: \n\n\nT-bone smile- he got explored\u2026I guess coz he\u2019s so darn c... http://t.co/QsTR2EGa","to_user_id":null,"to_user_id_str":null},{"created_at":"Sat, 17 Sep 2011 23:42:03 +0000","from_user":"UptownCloset","from_user_id":105071600,"from_user_id_str":"105071600","geo":null,"id":115208927842549760,"id_str":"115208927842549760","iso_language_code":"en","metadata":{"result_type":"recent"},"profile_image_url":"http://a2.twimg.com/profile_images/776068042/Shopping20Logo20TSS_normal.jpg","source":"&lt;a href=&quot;http://twitterfeed.com&quot; rel=&quot;nofollow&quot;&gt;twitterfeed&lt;/a&gt;","text":"This background TOTALLY distracts from my cuteness.: \n\n\nT-bone smile- he got explored\u2026I guess coz he\u2019s so darn c... http://t.co/iDRURPTy","to_user_id":null,"to_user_id_str":null},{"created_at":"Sat, 17 Sep 2011 23:42:03 +0000","from_user":"maddisonfoster","from_user_id":132280462,"from_user_id_str":"132280462","geo":null,"id":115208927821574144,"id_str":"115208927821574144","iso_language_code":"en","metadata":{"result_type":"recent"},"profile_image_url":"http://a0.twimg.com/profile_images/1065898269/n757108587_824998_9871_normal.jpg","source":"&lt;a href=&quot;http://twitterfeed.com&quot; rel=&quot;nofollow&quot;&gt;twitterfeed&lt;/a&gt;","text":"This background TOTALLY distracts from my cuteness.: \n\n\nT-bone smile- he got explored\u2026I guess coz he\u2019s so darn c... http://t.co/6gh0kpSq","to_user_id":null,"to_user_id_str":null},{"created_at":"Sat, 17 Sep 2011 23:41:49 +0000","from_user":"CuteOverload","from_user_id":692409,"from_user_id_str":"692409","geo":null,"id":115208867813654529,"id_str":"115208867813654529","iso_language_code":"en","metadata":{"result_type":"recent"},"profile_image_url":"http://a1.twimg.com/profile_images/97078327/co_normal.png","source":"&lt;a href=&quot;http://publicize.wp.com/&quot; rel=&quot;nofollow&quot;&gt;WordPress.com&lt;/a&gt;","text":"This background TOTALLY distracts from my cuteness. http://t.co/nKfFdOM3","to_user_id":null,"to_user_id_str":null},{"created_at":"Sat, 17 Sep 2011 23:37:42 +0000","from_user":"junkshop_coyote","from_user_id":112497449,"from_user_id_str":"112497449","geo":null,"id":115207834215526401,"id_str":"115207834215526401","iso_language_code":"en","metadata":{"result_type":"recent"},"profile_image_url":"http://a1.twimg.com/profile_images/1515138673/jc_by_vermyfox_normal.jpg","source":"&lt;a href=&quot;http://twitter.com/tweetbutton&quot; rel=&quot;nofollow&quot;&gt;Tweet Button&lt;/a&gt;","text":"AWWW. #ThatIsAll http://t.co/4JqTpcPt","to_user_id":null,"to_user_id_str":null},{"created_at":"Sat, 17 Sep 2011 23:32:36 +0000","from_user":"yoda316","from_user_id":23004991,"from_user_id_str":"23004991","geo":null,"id":115206550284546048,"id_str":"115206550284546048","iso_language_code":"en","metadata":{"result_type":"recent"},"profile_image_url":"http://a3.twimg.com/profile_images/1423254295/269697_10150247780827748_558322747_7328726_6463116_n_normal.jpg","source":"&lt;a href=&quot;http://twitter.com/tweetbutton&quot; rel=&quot;nofollow&quot;&gt;Tweet Button&lt;/a&gt;","text":"You've Gone Too Far, George Lucas http://t.co/0E8jo6Qp","to_user_id":null,"to_user_id_str":null},{"created_at":"Sat, 17 Sep 2011 23:21:37 +0000","from_user":"nicoleaxelrod1","from_user_id":390402272,"from_user_id_str":"390402272","geo":null,"id":115203783658708992,"id_str":"115203783658708992","iso_language_code":"en","metadata":{"result_type":"recent"},"profile_image_url":"http://a2.twimg.com/profile_images/1503722978/Nicole1_normal.jpg","source":"&lt;a href=&quot;http://twitter.com/&quot;&gt;web&lt;/a&gt;","text":"RT @TheGregoryBlair: OMG! Hilarious (fake) #StarWars action...with Jedi kittens!  http://t.co/O7V7QCkT","to_user_id":null,"to_user_id_str":null},{"created_at":"Sat, 17 Sep 2011 23:18:49 +0000","from_user":"tripleoverload","from_user_id":571463,"from_user_id_str":"571463","geo":null,"id":115203080039038977,"id_str":"115203080039038977","iso_language_code":"en","metadata":{"result_type":"recent"},"profile_image_url":"http://a1.twimg.com/profile_images/28458812/baru_1_normal.jpg","source":"&lt;a href=&quot;http://twitterfeed.com&quot; rel=&quot;nofollow&quot;&gt;twitterfeed&lt;/a&gt;","text":"[cute*] LOLpug = Little Old Lady Pug http://t.co/VFI3Bzfn","to_user_id":null,"to_user_id_str":null},{"created_at":"Sat, 17 Sep 2011 23:14:17 +0000","from_user":"TheGregoryBlair","from_user_id":258162966,"from_user_id_str":"258162966","geo":null,"id":115201941071601665,"id_str":"115201941071601665","iso_language_code":"en","metadata":{"result_type":"recent"},"profile_image_url":"http://a0.twimg.com/profile_images/1517778962/GB4BF_normal.jpg","source":"&lt;a href=&quot;http://twitter.com/&quot;&gt;web&lt;/a&gt;","text":"OMG! Hilarious (fake) #StarWars action...with Jedi kittens!  http://t.co/O7V7QCkT","to_user_id":null,"to_user_id_str":null},{"created_at":"Sat, 17 Sep 2011 23:10:22 +0000","from_user":"chloemcgill","from_user_id":117509280,"from_user_id_str":"117509280","geo":null,"id":115200955066220544,"id_str":"115200955066220544","iso_language_code":"en","metadata":{"result_type":"recent"},"profile_image_url":"http://a1.twimg.com/profile_images/1152153353/frog_normal.jpg","source":"&lt;a href=&quot;http://www.feedblitz.com/f/f.fbz?help/default#twitter&quot; rel=&quot;nofollow&quot;&gt;FeedBlitz&lt;/a&gt;","text":"LOLpug = Little Old Lady Pug via Cute Overload - Honeychild where's your fashion sense?! I have NO PEARLS to ... http://t.co/jVaIjQ93","to_user_id":null,"to_user_id_str":null},{"created_at":"Sat, 17 Sep 2011 23:05:19 +0000","from_user":"theresamax","from_user_id":226308648,"from_user_id_str":"226308648","geo":null,"id":115199683449724928,"id_str":"115199683449724928","iso_language_code":"en","metadata":{"result_type":"recent"},"profile_image_url":"http://a2.twimg.com/profile_images/1429763433/image_normal.jpg","source":"&lt;a href=&quot;http://twitter.com/#!/download/iphone&quot; rel=&quot;nofollow&quot;&gt;Twitter for iPhone&lt;/a&gt;","text":"RT\u201C@eweirdworld: LOLpug = Little Old Lady Pug: Honeychild where\u2019s your fashion sense?! I have NO PEARLS to clutch!\n... http://t.co/DX7pCPIu","to_user_id":null,"to_user_id_str":null}],"results_per_page":100,"since_id":0,"since_id_str":"0"}